asciimath_printer.py
latex2sympy2.py
gen/PSLexer.py
gen/PSListener.py
gen/PSParser.py
gen/__init__.py
tests/__init__.py
tests/abs_test.py
tests/all_bad_test.py
tests/all_good_test.py
tests/atom_expr_test.py
tests/binomial_test.py
tests/ceil_test.py
tests/complex_test.py
tests/context.py
tests/exp_test.py
tests/floor_test.py
tests/gcd_test.py
tests/greek_test.py
tests/grouping_test.py
tests/lcm_test.py
tests/left_right_cdot_test.py
tests/linalg_test.py
tests/max_test.py
tests/min_test.py
tests/mod_test.py
tests/overline_test.py
tests/pi_test.py
tests/trig_test.py
tests/variable_test.py
latex2sympy2_llmmath-1.9.1.dist-info/LICENSE.txt
latex2sympy2_llmmath-1.9.1.dist-info/METADATA
latex2sympy2_llmmath-1.9.1.dist-info/WHEEL
latex2sympy2_llmmath-1.9.1.dist-info/top_level.txt
latex2sympy2_llmmath-1.9.1.dist-info/RECORD
